
{
    "visits": [
      {
        "id": 1,
        "customer_id": 1,
        "visit_date": "2025-06-20T10:30:00.000Z",
        "status": "Completed",
        "location": "Acme Corporation HQ, Downtown",
        "notes": "Successful product demo. Customer showed high interest in our enterprise solution.",
        "activities_done": ["1", "2"],
        "created_at": "2025-06-18T09:15:00.000Z"
      },
      {
        "id": 2,
        "customer_id": 2,
        "visit_date": "2025-06-21T14:00:00.000Z",
        "status": "Completed",
        "location": "Tech Solutions Office, Business Park",
        "notes": "Technical consultation completed. Provided detailed system requirements.",
        "activities_done": ["2", "6"],
        "created_at": "2025-06-19T11:30:00.000Z"
      },
      {
        "id": 3,
        "customer_id": 3,
        "visit_date": "2025-06-22T09:00:00.000Z",
        "status": "Pending",
        "location": "Global Industries Main Office",
        "notes": "Scheduled for contract discussion and pricing negotiation.",
        "activities_done": [],
        "created_at": "2025-06-20T16:45:00.000Z"
      },
      {
        "id": 4,
        "customer_id": 4,
        "visit_date": "2025-06-19T11:30:00.000Z",
        "status": "Completed",
        "location": "Metro Services Warehouse",
        "notes": "System installation completed successfully. Training provided to staff.",
        "activities_done": ["7", "6"],
        "created_at": "2025-06-17T08:20:00.000Z"
      },
      {
        "id": 5,
        "customer_id": 5,
        "visit_date": "2025-06-23T13:15:00.000Z",
        "status": "Pending",
        "location": "Innovation Hub Conference Room",
        "notes": "Follow-up meeting to discuss implementation timeline.",
        "activities_done": [],
        "created_at": "2025-06-21T14:10:00.000Z"
      },
      {
        "id": 6,
        "customer_id": 1,
        "visit_date": "2025-06-18T15:45:00.000Z",
        "status": "Completed",
        "location": "Acme Corporation Branch Office",
        "notes": "Maintenance check completed. All systems running optimally.",
        "activities_done": ["8"],
        "created_at": "2025-06-16T12:30:00.000Z"
      },
      {
        "id": 7,
        "customer_id": 6,
        "visit_date": "2025-06-24T10:00:00.000Z",
        "status": "Pending",
        "location": "Prime Enterprises Head Office",
        "notes": "Initial sales presentation scheduled.",
        "activities_done": [],
        "created_at": "2025-06-22T09:45:00.000Z"
      },
      {
        "id": 8,
        "customer_id": 7,
        "visit_date": "2025-06-17T16:30:00.000Z",
        "status": "Cancelled",
        "location": "Future Systems Office",
        "notes": "Meeting cancelled due to client emergency. Rescheduling required.",
        "activities_done": [],
        "created_at": "2025-06-15T13:20:00.000Z"
      },
      {
        "id": 9,
        "customer_id": 8,
        "visit_date": "2025-06-21T08:30:00.000Z",
        "status": "Completed",
        "location": "Blue Ocean Technologies Lab",
        "notes": "Problem resolution session. Issue with integration resolved successfully.",
        "activities_done": ["5", "2"],
        "created_at": "2025-06-19T15:55:00.000Z"
      },
      {
        "id": 10,
        "customer_id": 2,
        "visit_date": "2025-06-25T11:00:00.000Z",
        "status": "Pending",
        "location": "Tech Solutions Remote Office",
        "notes": "Customer feedback collection session planned.",
        "activities_done": [],
        "created_at": "2025-06-23T10:15:00.000Z"
      }
    ]
  }